ephemeris/__init__.py
ephemeris/_config_models.py
ephemeris/_idc_data_managers_to_tools.py
ephemeris/_idc_lint.py
ephemeris/_idc_split_data_manager_genomes.py
ephemeris/common_parser.py
ephemeris/ephemeris_log.py
ephemeris/generate_tool_list_from_ga_workflow_files.py
ephemeris/get_tool_list_from_galaxy.py
ephemeris/install_tool_deps.py
ephemeris/run_data_managers.py
ephemeris/set_library_permissions.py
ephemeris/setup_data_libraries.py
ephemeris/shed_tools.py
ephemeris/shed_tools_args.py
ephemeris/shed_tools_methods.py
ephemeris/sleep.py
ephemeris/workflow_install.py
ephemeris-0.10.10.dist-info/LICENSE
ephemeris-0.10.10.dist-info/METADATA
ephemeris-0.10.10.dist-info/WHEEL
ephemeris-0.10.10.dist-info/entry_points.txt
ephemeris-0.10.10.dist-info/top_level.txt
ephemeris-0.10.10.dist-info/RECORD
