Metadata-Version: 2.1
Name: ephemeris
Version: 0.10.10
Summary: Ephemeris is an opinionated library and set of scripts for managing the bootstrapping of Galaxy project plugins - tools, index data, and workflows.
Home-page: https://github.com/galaxyproject/ephemeris
Author: Galaxy Project and Community
Author-email: jmchilton@gmail.com
License: AFL
Keywords: galaxy
Classifier: Development Status :: 5 - Production/Stable
Classifier: Intended Audience :: Developers
Classifier: Environment :: Console
Classifier: License :: OSI Approved :: Academic Free License (AFL)
Classifier: Operating System :: POSIX
Classifier: Topic :: Software Development
Classifier: Topic :: Software Development :: Code Generators
Classifier: Topic :: Software Development :: Testing
Classifier: Natural Language :: English
Classifier: Programming Language :: Python :: 3
Classifier: Programming Language :: Python :: 3.7
Classifier: Programming Language :: Python :: 3.8
Classifier: Programming Language :: Python :: 3.9
Classifier: Programming Language :: Python :: 3.10
Requires-Python: >=3.7
License-File: LICENSE
Requires-Dist: six >=1.9.0
Requires-Dist: PyYAML
Requires-Dist: bioblend >=0.10.0
Requires-Dist: Jinja2
Requires-Dist: galaxy-tool-util >=20.9.1
Requires-Dist: galaxy-util >=20.9.0
Requires-Dist: pysam
Requires-Dist: rich
